porthamiltonians/__init__.py
porthamiltonians/control/__init__.py
porthamiltonians/control/casadiNN.py
porthamiltonians/control/casadiPH.py
porthamiltonians/control/mpc.py
porthamiltonians/control/phcontroller.py
porthamiltonians/control/pid.py
porthamiltonians/control/reference.py
porthamiltonians/phnns/__init__.py
porthamiltonians/phnns/dynamic_system_neural_network.py
porthamiltonians/phnns/models.py
porthamiltonians/phnns/port_hamiltonian_neural_network.py
porthamiltonians/phnns/train_utils.py
porthamiltonians/phsystems/__init__.py
porthamiltonians/phsystems/msd_system.py
porthamiltonians/phsystems/port_Hamiltonian_system.py
porthamiltonians/phsystems/tank_system.py
porthamiltonians/utils/__init__.py
porthamiltonians/utils/derivatives.py
porthamiltonians/utils/utils.py
porthamiltonians-1.1.0.dist-info/LICENSE.txt
porthamiltonians-1.1.0.dist-info/METADATA
porthamiltonians-1.1.0.dist-info/WHEEL
porthamiltonians-1.1.0.dist-info/top_level.txt
porthamiltonians-1.1.0.dist-info/RECORD
