Metadata-Version: 2.1
Name: porthamiltonians
Version: 1.1.0
Summary: A package for simulating and learning port-Hamiltonian systems. For further details, see https://arxiv.org/pdf/2206.02660.pdf
Home-page: https://gitlab.sintef.no/hybrid-machine-learning/port-hamiltonian-neural-networks
Author: Sølve Eidnes
Author-email: solve.eidnes@sintef.no
License: MIT
Keywords: port Hamiltonian neural networks
Classifier: Development Status :: 5 - Production/Stable
License-File: LICENSE.txt
Requires-Dist: networkx
Requires-Dist: numpy
Requires-Dist: torch
Requires-Dist: torchaudio
Requires-Dist: torchvision
Requires-Dist: scipy
Requires-Dist: casadi
Requires-Dist: do-mpc
